policytool/__init__.py
policytool/atlas.py
policytool/cli.py
policytool/configfile.py
policytool/hive.py
policytool/policycache.py
policytool/policyutil.py
policytool/ranger.py
policytool/rangersync.py
policytool/tagsync.py
policytool/template.py
policytool/urlutil.py
tests/__init__.py
tests/test_hive.py
tests/test_policycache.py
tests/test_policyutil.py
tests/test_rangersync.py
tests/test_tagsync.py
cobra_policytool-1.1.6.dist-info/LICENSE.txt
cobra_policytool-1.1.6.dist-info/METADATA
cobra_policytool-1.1.6.dist-info/WHEEL
cobra_policytool-1.1.6.dist-info/entry_points.txt
cobra_policytool-1.1.6.dist-info/top_level.txt
cobra_policytool-1.1.6.dist-info/RECORD
