Metadata-Version: 2.1
Name: cobra-policytool
Version: 1.1.6
Summary: Tool for manage Hadoop access using Apache Atlas and Ranger.
Home-page: https://github.com/SvenskaSpel/cobra-policytool
Author: Magnus Runesson
Author-email: Magnus.Runesson@svenskaspel.se
License: Apache 2.0
Platform: UNKNOWN
Classifier: Environment :: Console
Classifier: Programming Language :: Python :: 2.7
Classifier: License :: OSI Approved :: Apache Software License
Classifier: Operating System :: OS Independent
Classifier: Topic :: Database
Classifier: Topic :: Security
Classifier: Topic :: Utilities
Requires-Dist: requests (>=2.20)
Requires-Dist: requests-kerberos
Requires-Dist: click
Requires-Dist: pyhive
Requires-Dist: thrift
Requires-Dist: thrift-sasl
Requires-Dist: sasl
